README.md
setup.py
afrelpl89_helloworld/__init__.py
afrelpl89_helloworld/sample.py
helloworld_by_afrelpl89.egg-info/PKG-INFO
helloworld_by_afrelpl89.egg-info/SOURCES.txt
helloworld_by_afrelpl89.egg-info/dependency_links.txt
helloworld_by_afrelpl89.egg-info/top_level.txt