Metadata-Version: 2.1
Name: helloworld-by-afrelpl89
Version: 1.0.1
Summary: Sample PYPI App
Home-page: UNKNOWN
License: UNKNOWN
Platform: UNKNOWN
